sqlfluff_templater_dataform/__init__.py
sqlfluff_templater_dataform/templater.py
sqlfluff_templater_dataform-0.1.7.dist-info/licenses/LICENSE.md
sqlfluff_templater_dataform-0.1.7.dist-info/METADATA
sqlfluff_templater_dataform-0.1.7.dist-info/WHEEL
sqlfluff_templater_dataform-0.1.7.dist-info/entry_points.txt
sqlfluff_templater_dataform-0.1.7.dist-info/top_level.txt
sqlfluff_templater_dataform-0.1.7.dist-info/RECORD
