Metadata-Version: 2.4
Name: sqlfluff-templater-dataform
Version: 0.1.7
Summary: Lint your dataform project SQL
Author: hiracky16
License: MIT License
Project-URL: Repository, https://github.com/hiracky16/sqlfluff-templater-dataform.git
Keywords: sqlfluff,sql,linter,formatter,bigquery,dataform
License-File: LICENSE.md
Requires-Dist: sqlfluff==3.5.0
Dynamic: license-file
